{"cameraMode":{"drawMode":0,"name":"Shaded","section":"Shading Mode"},"sceneLighting":true,"audioPlay":false,"sceneViewState":{"m_AlwaysRefresh":false,"showFog":true,"showSkybox":true,"showFlares":true,"showImageEffects":true,"showParticleSystems":true,"showVisualEffectGraphs":true,"m_FxEnabled":true},"in2DMode":false,"pivot":{"x":-11.826299667358399,"y":2.8582658767700197,"z":5.158198356628418},"rotation":{"x":-0.3925754129886627,"y":0.01792994886636734,"z":-0.007655291352421045,"w":-0.9195168614387512},"size":8.407005310058594,"orthographic":false}